llm_inflation/__init__.py
llm_inflation/data/covariates.csv
llm_inflation/data.py
llm_inflation/llm.py
llm_inflation/model/__init__.py
llm_inflation/model/multivariate.py
llm_inflation/utils.py
llm_inflation-0.1.6.dist-info/METADATA
llm_inflation-0.1.6.dist-info/WHEEL
llm_inflation-0.1.6.dist-info/RECORD
